chorogrid/Chorogrid.py
chorogrid/Colorbin.py
chorogrid/__init__.py
chorogrid/databases/canada_federal_ridings.csv
chorogrid/databases/canada_federal_ridings_column_descriptions.txt
chorogrid/databases/canada_provinces.csv
chorogrid/databases/canada_provinces_column_descriptions.txt
chorogrid/databases/europe_countries.csv
chorogrid/databases/europe_countries_column_descriptions.txt
chorogrid/databases/usa_counties.csv
chorogrid/databases/usa_counties_column_descriptions.txt
chorogrid/databases/usa_counties_statelines.txt
chorogrid/databases/usa_states.csv
chorogrid/databases/usa_states_column_descriptions.txt
chorogrid/sample_data/TRANSPOSITION_338FED.csv
chorogrid/sample_data/sample_county_data.csv
chorogrid/sample_data/sample_europe_data.csv
chorogrid/sample_data/sample_state_data.csv
chorogrid/sample_data/state_flowers.csv
chorogrid/sample_data/state_trees.csv
chorogrid-0.0.1.dist-info/WHEEL
chorogrid-0.0.1.dist-info/METADATA
chorogrid-0.0.1.dist-info/RECORD
