Metadata-Version: 1.2
Name: chorogrid
Version: 0.0.1
Summary: A python script to produce choropleths and colored square- and hex-grid maps
Home-page: https://github.com/Prooffreader/chorogrid
License: UNKNOWN
Author: David Taylor
Author-email: prooffreader@gmail.com
Classifier: License :: OSI Approved :: MIT License
Requires-Dist: pandas
